{
  "albumId": "00000001",
  "album_title": "不仅仅是喜欢",
  "cover_url_large": "https://cn.bing.com//th?id=OHR.RainbowMarmot_ZH-CN4605973404_1920x1080.jpg",
  "cover_url_small": "https://cn.bing.com//th?id=OHR.RainbowMarmot_ZH-CN4605973404_1920x1080.jpg",
  "cover_url_middle": "https://cn.bing.com//th?id=OHR.RainbowMarmot_ZH-CN4605973404_1920x1080.jpg",
  "album_tags": "00000001",
  "album_intro": "在对的时间,遇见最美的你",
  "play_count": "100",
  "include_track_count": "50",
  "announcer": {
    "nickname": "网络歌曲"
  }
}
